safedit/__init__.py
safedit/app.py
safedit/cli.py
safedit/crdt.py
safedit/main.py
safedit/socket_handlers.py
safedit/state.py
safedit/utils.py
safedit/watcher.py
safedit/static/index.html
safedit/static/assets/abap-HeDQy6fh.js
safedit/static/assets/apex-CbmXAvAW.js
safedit/static/assets/azcli-BPy9tPO_.js
safedit/static/assets/bat-C2kkMZXD.js
safedit/static/assets/bicep-STK2XETz.js
safedit/static/assets/cameligo-D88lnp7m.js
safedit/static/assets/clojure-BVXjUq6W.js
safedit/static/assets/codicon-Hscy-R9e.ttf
safedit/static/assets/coffee-BRG4GrUX.js
safedit/static/assets/cpp-DeB58NaV.js
safedit/static/assets/csharp-DWSjX1vK.js
safedit/static/assets/csp-C2dP3GFv.js
safedit/static/assets/css-1NjUY7wv.js
safedit/static/assets/cssMode-Bu71LKLf.js
safedit/static/assets/cypher-CvujjWtm.js
safedit/static/assets/dart-BE_rHeGz.js
safedit/static/assets/dockerfile-DU9BjHlP.js
safedit/static/assets/ecl-hUW-QHbE.js
safedit/static/assets/elixir-BAkJxX25.js
safedit/static/assets/flow9-C5jFnEuB.js
safedit/static/assets/freemarker2-Bij4q31Y.js
safedit/static/assets/fsharp-CCzPE5Ie.js
safedit/static/assets/go-BJDrqb1l.js
safedit/static/assets/graphql-DeqjH8oo.js
safedit/static/assets/handlebars-3c2Ut9Eg.js
safedit/static/assets/hcl-fhYSe8Ik.js
safedit/static/assets/html-Cl_GyBO0.js
safedit/static/assets/htmlMode-BgdLhQcW.js
safedit/static/assets/index-CVYVSCDA.css
safedit/static/assets/index-oHMXTJxd.js
safedit/static/assets/ini-bfKW7yAs.js
safedit/static/assets/java-89tSEgoR.js
safedit/static/assets/javascript-BpkSYrBY.js
safedit/static/assets/jsonMode-iXO-y40f.js
safedit/static/assets/julia-CULLjdBi.js
safedit/static/assets/kotlin-bF-WLz8W.js
safedit/static/assets/less-BcX_owYs.js
safedit/static/assets/lexon-Bgb1VazO.js
safedit/static/assets/liquid-CsV9keRX.js
safedit/static/assets/lua-D4wIloCQ.js
safedit/static/assets/m3-CIXVZ5K0.js
safedit/static/assets/markdown-C2pIiAgT.js
safedit/static/assets/mdx-DBts_eit.js
safedit/static/assets/mips-DDY3B9Me.js
safedit-0.1.2.dist-info/METADATA
safedit-0.1.2.dist-info/WHEEL
safedit-0.1.2.dist-info/entry_points.txt
safedit-0.1.2.dist-info/top_level.txt
safedit-0.1.2.dist-info/RECORD
